README.md
setup.cfg
setup.py
BackupTree.egg-info/PKG-INFO
BackupTree.egg-info/SOURCES.txt
BackupTree.egg-info/dependency_links.txt
BackupTree.egg-info/entry_points.txt
BackupTree.egg-info/requires.txt
BackupTree.egg-info/top_level.txt
backupTree/__init__.py
backupTree/backupTree.py