Metadata-Version: 2.1
Name: BackupTree
Version: 0.0.1
Summary: This project is to create the directory tree to upload your project to Pypi
Home-page: https://github.com/batestin1/
Author: Maycon Cypriano Batestin
Author-email: mayconcipriano@gmail.com
Project-URL: Código fonte, https://github.com/batestin1/
Project-URL: Download, https://github.com/batestin1/
Keywords: directory tree backup
Classifier: Programming Language :: Python :: 3
Classifier: License :: OSI Approved :: MIT License
Classifier: Operating System :: OS Independent
Requires-Python: >=3.6
Requires-Dist: pywin32
